easyprintstr/__init__.py
easyprintstr/printer.py
easyprintstr-0.1.0.dist-info/LICENSE
easyprintstr-0.1.0.dist-info/METADATA
easyprintstr-0.1.0.dist-info/WHEEL
easyprintstr-0.1.0.dist-info/top_level.txt
easyprintstr-0.1.0.dist-info/RECORD
