Metadata-Version: 2.2
Name: easyprintstr
Version: 0.1.0
Summary: A simple package to print text with a border.
Home-page: https://github.com/l1nyuan7/easyprintstr
Author: l1nyuan7
Author-email: linyuan@gmail.com
License: MIT
Classifier: Programming Language :: Python :: 3
Classifier: License :: OSI Approved :: MIT License
Classifier: Operating System :: OS Independent
Requires-Python: >=3.6
License-File: LICENSE
Dynamic: author
Dynamic: author-email
Dynamic: classifier
Dynamic: description
Dynamic: description-content-type
Dynamic: home-page
Dynamic: license
Dynamic: requires-python
Dynamic: summary
